screenenv/__init__.py
screenenv/logger.py
screenenv/mcp_remote_server.py
screenenv/remote_screen_env.py
screenenv/response_models.py
screenenv/retry_decorator.py
screenenv/sandbox.py
screenenv/test_sandbox.py
screenenv/desktop_agent/desktop_agent_base.py
screenenv/remote_provider/__init__.py
screenenv/remote_provider/create_remote_env.py
screenenv/remote_provider/provider.py
screenenv/remote_provider/docker/provider.py
screenenv-0.1.2.dist-info/METADATA
screenenv-0.1.2.dist-info/WHEEL
screenenv-0.1.2.dist-info/RECORD
